{
  "date": "2026-07-02",
  "location": "DMC첨단산업센터",
  "lat": 37.5845,
  "lng": 126.8856,
  "generatedAt": "2026-07-02T06:03:33+09:00",
  "periods": [
    {
      "time": "06:00",
      "label": "오전",
      "temp": 22,
      "sky": "흐림",
      "pop": 30,
      "pty": "없음"
    },
    {
      "time": "07:00",
      "label": "오전",
      "temp": 23,
      "sky": "흐림",
      "pop": 30,
      "pty": "없음"
    },
    {
      "time": "08:00",
      "label": "오전",
      "temp": 24,
      "sky": "구름많음",
      "pop": 20,
      "pty": "없음"
    },
    {
      "time": "09:00",
      "label": "오전",
      "temp": 25,
      "sky": "맑음",
      "pop": 0,
      "pty": "없음"
    },
    {
      "time": "10:00",
      "label": "오전",
      "temp": 26,
      "sky": "맑음",
      "pop": 0,
      "pty": "없음"
    },
    {
      "time": "11:00",
      "label": "오전",
      "temp": 27,
      "sky": "맑음",
      "pop": 0,
      "pty": "없음"
    },
    {
      "time": "12:00",
      "label": "오후",
      "temp": 28,
      "sky": "흐림",
      "pop": 30,
      "pty": "없음"
    },
    {
      "time": "13:00",
      "label": "오후",
      "temp": 29,
      "sky": "흐림",
      "pop": 30,
      "pty": "없음"
    }
  ],
  "highlights": {
    "tempMin": 22,
    "tempMax": 29
  },
  "summary": "오늘 22~29°C. 출근은 흐림이나 비 없고 9시쯤 맑아짐. 오후 흐리고 강수 30% — 퇴근 때 우산 챙기세요."
}
