{
  "date": "2026-07-09",
  "generatedAt": "2026-07-09T07:03:05+09:00",
  "markets": {
    "kr": {
      "summary": "어제 코스피·코스닥 급락 여파로 투자심리가 위축됐고, 코스닥은 10개월 만에 800선을 내주며 거래대금도 나흘째 7조 원 아래입니다. 오늘(10일) SK하이닉스 나스닥 ADR 상장을 앞두고 달러 유입 기대에 원·달러가 1490원대로 내려왔고 외국인 순매수 전환도 주목됩니다. 상장폐지 요건 강화 이후 주식병합 공시가 급증했고, 제약주 공매도 확대와 삼전·하이닉스 레버리지 ETF 논란이 불안 요인으로 거론됩니다.",
      "items": [
        {
          "title": "상장폐지 공포에 주식병합 24배 ‘급증’…계열사 합병도 잇따라",
          "link": "https://www.dnews.co.kr/uhtml/view.jsp?idxno=202607081328591690405",
          "description": "상장사 주식병합 공시 240건 기록…지난해 동기 10건 대비 24배 급증 휴맥스·엔피 등 시가총액 요건 미달 피하기 위한 계열사 흡수합병도 부실기업 퇴출을 위한 상장폐지 요건 강화 이후 국내 상장사의 주식병합 결의...",
          "pubDate": "Thu, 09 Jul 2026 07:00:00 +0900"
        },
        {
          "title": "\"SK하이닉스 40조 달러 유입 기대\"...환율 장중 1490원대로 '뚝'",
          "link": "https://www.ebn.co.kr/news/articleView.html?idxno=1715641",
          "description": "SK하이닉스의 미국 나스닥 미국주식예탁증서(ADR) 상장을 앞두고 대규모 달러 자금 유입 기대가 커진 데다 외국인 투자자가 국내 증시에서 순매수로 돌아서면서 환율 하락을 이끌었다. 8일 서울외환시장에서 원·달러...",
          "pubDate": "Thu, 09 Jul 2026 06:52:00 +0900"
        },
        {
          "title": "한시금지? 유한양행 덮친 공매도, 서정진도 불만 \"하락주범 vs 거품제거...",
          "link": "https://n.news.naver.com/mnews/article/417/0001150898?sid=101",
          "description": "커지는 공매도 비중…유한·녹십자·삼성에피스 타깃 9일 한국거래소에 따르면 올 들어 국내 주요 제약... 공매도는 주식을 빌려 먼저 매도한 뒤 추후 다시 매수하는 투자기법이다. 주가가 내릴수록 이득을 보고 주가가...",
          "pubDate": "Thu, 09 Jul 2026 06:51:00 +0900"
        },
        {
          "title": "경상수지 '최대 흑자'인데…증시는 동반 하락",
          "link": "https://n.news.naver.com/mnews/article/055/0001370941?sid=101",
          "description": "미국주식예탁증서, ADR 상장과 미국 빅테크 기업들의 실적 발표가 증시의 주요 변수로 꼽힙니다. SK하이닉스의 ADR 상장이 국내 투자 심리 회복으로 이어질 거라는 기대와 함께 외국인 투자자의 이탈을 가속화할 수...",
          "pubDate": "Thu, 09 Jul 2026 06:33:00 +0900"
        },
        {
          "title": "대기업 사업재편 이끈 변호사들…7대 로펌 라이징스타는 [시그널 선정 ...",
          "link": "https://n.news.naver.com/mnews/article/011/0004639693?sid=101",
          "description": "△HD현대중공업·HD현대미포 합병 △영풍·MBK파트너스의 고려아연 주식 공개매수 등 굵직한 거래를 자문했다. 국내 최대 규모로 평가되는 HD현대 합병 자문 당시 다국적 규제와 변수를 고려해 거래 전 과정을 총괄하고...",
          "pubDate": "Thu, 09 Jul 2026 06:31:00 +0900"
        },
        {
          "title": "커지는 삼전닉스 2배 ETF 퇴출론… 현실적 대안은 [레버리지 리스크 ⑦...",
          "link": "https://it.chosun.com/news/articleView.html?idxno=2023092165399",
          "description": "9일 금융투자업계에 따르면 한국은행은 지난 5일 박성훈 국민의힘 의원실에 제출한 답변서에서 \"삼성전자와 SK하이닉스의 시가총액과 거래 규모가 국내 주식 시장의 절반 이상을 차지하는 상황에서 단일종목 레버리지...",
          "pubDate": "Thu, 09 Jul 2026 06:30:00 +0900"
        },
        {
          "title": "[기획] 토니모리 오너 일가의 기막힌 부의 증식… 상장사 이익은 '배당...",
          "link": "https://www.nbntv.co.kr/news/articleView.html?idxno=4022847",
          "description": "기자 |국내 1세대 뷰티 로드샵 브랜드로 K-뷰티를 이끌어온 토니모리가 총수 일가의 과도한 사익 편취... 지분 27.81%를 보유한 최대주주 배해동 회장을 비롯해 총수 일가가 보유한 주식은 총 1275만 주(53%)로, 이미 전체...",
          "pubDate": "Thu, 09 Jul 2026 06:20:00 +0900"
        },
        {
          "title": "외국인 주식 거래 증가로 한국 금융서비스수지 사상 최대 기록",
          "link": "https://www.tokenpost.kr/news/economy/376075",
          "description": "올해 외국인의 국내 주식 거래가 늘면서 우리나라 금융서비스수지가 2026년 5월 사상 최대 규모로 커졌다. 주식 매매가 활발해질수록 국내 증권사와 금융회사가 받는 거래 수수료 수입도 함께 증가하는데, 최근에는...",
          "pubDate": "Thu, 09 Jul 2026 06:14:00 +0900"
        },
        {
          "title": "스페이스X의 굴욕… 결국 상장가 밑으로 추락",
          "link": "https://n.news.naver.com/mnews/article/029/0003036106?sid=101",
          "description": "7% 올랐다. 마이크론도 1.11% 올랐다. 샌디스크는 6.77% 급등했다. 필라델피아 반도체 지수는 2.2% 상승했다. 반도체 종목이 회복세를 보이멩 따라 오늘 코스피에서 삼성전자와 SK하이닉스의 반등 여부가 주목된다.",
          "pubDate": "Thu, 09 Jul 2026 06:43:00 +0900"
        },
        {
          "title": "보안사고 커지는데… 4대 은행, 정보보호 투자비중 되레 줄어",
          "link": "https://it.chosun.com/news/articleView.html?idxno=2023092165407",
          "description": "개정안은 기존 '매출 3000억원 이상' 요건을 폐지하고 코스피·코스닥 상장사 전체와 ISMS(정보보호 관리체계) 인증 의무 기업, 금융회사까지 공시 의무 대상에 포함하는 내용을 담고 있다. 개정안은 2027년부터 적용될...",
          "pubDate": "Thu, 09 Jul 2026 06:40:00 +0900"
        },
        {
          "title": "GS샵, 본격 무더위에 \"선글라스 주문액 214.2%↑\"",
          "link": "http://www.biztribune.co.kr/news/articleView.html?idxno=355706",
          "description": "2만6050원의 고점을 찍고 2만4600원까지 떨어지는 등 등락을 보였다. 코스피가 5% 이상 하락하면서 오후 1시 반 매도 사이트카가 발동된 데 영향을 받은 것으로 보인다. 네이버증권 [비즈트리뷴=]",
          "pubDate": "Thu, 09 Jul 2026 06:38:00 +0900"
        },
        {
          "title": "코스피·코스닥 전 거래일(8일) 주요공시는?...기아, 송호성·송민수 각...",
          "link": "https://www.pinpointnews.co.kr/news/articleView.html?idxno=466821",
          "description": "5%\" ▲ 삼성중공업[010140], 연간 수주 5년만에 100억달러 돌파 ▲ ESG 공시, 10조이상 코스피 상장사 내후년부터 사업보고서 의무 ▲ KB증권 \"카카오[035720], AI 사업성과 입증 필요…목표주가 하향\"",
          "pubDate": "Thu, 09 Jul 2026 06:36:00 +0900"
        },
        {
          "title": "휠라 언더웨어, \"'러버스' 전년동기대비 277% 성장\"",
          "link": "http://www.biztribune.co.kr/news/articleView.html?idxno=355672",
          "description": "이날 코스피가 4% 넘게 하락하며 오후 1시 31분 매도 사이드카가 발동되는 등 일제히 주가가 떨어지는 모습을 보이는 가운데 미스토홀딩스 주가는 방어되고 있다. 네이버증권 [비즈트리뷴=]",
          "pubDate": "Thu, 09 Jul 2026 06:36:00 +0900"
        },
        {
          "title": "지씨셀, 국내 바이오 4사와 세포·유전자치료제 협력체계 구축",
          "link": "http://www.biztribune.co.kr/news/articleView.html?idxno=355681",
          "description": "13%)떨어진 것으로 1만4400원까지 올랐다가 1만3360원까지 떨어지는 등 등락을 보였다. 이날 코스피 지수가 5% 급락하며 매도 사이드카가 발동한 날이여서 이에 따른 영향을 받은 것으로 보인다. 네이버증권 [비즈트리뷴=]",
          "pubDate": "Thu, 09 Jul 2026 06:34:00 +0900"
        },
        {
          "title": "10개월 만에 800선 내준 코스닥…거래대금 나흘째 7조 밑돌아 [코주부]",
          "link": "https://n.news.naver.com/mnews/article/011/0004639690?sid=101",
          "description": "코스닥지수가 10개월 만에 800선을 내주며 마감했다. 거래대금도 나흘 연속 7조 원을 밑돌며 투자심리가 빠르게 얼어붙는 모습이다. 지난달 말 코스피에서 빠져나온 자금이 코스닥으로 유입되며 나타났던 ‘순환매’...",
          "pubDate": "Thu, 09 Jul 2026 06:17:00 +0900"
        }
      ]
    },
    "us": {
      "summary": "미·이란 긴장 재점화와 유가 급등으로 8일(美) 뉴욕증시는 혼조 마감했습니다. 다우는 1% 넘게 하락했고 S&P500도 약세였으나, 엔비디아·마이크론 등 반도체주 반등이 나스닥을 0.2% 소폭 상승으로 끌어올렸습니다. SK하이닉스의 10일(現地) 나스닥 ADR 상장과 빅테크 실적 가이던스가 오늘 장의 핵심 변수이며, 스페이스X는 상장 후 주가가 공모가 아래로 내려왔습니다.",
      "items": [
        {
          "title": "[김재근 칼럼] 장관 없는 만기친람의 시대",
          "link": "https://n.news.naver.com/mnews/article/656/0000181061?sid=110",
          "description": "내란의 생채기도 이겨냈고, 미국-이란전쟁의 수렁도 잘 빠져나왔다. 어물어물 5년을 허송한 문재인 정부나... '빚투'가 성행하고 온 국민이 아침 저녁으로 삼성전자와 SK하이닉스의 주가를 묻는 '주식공화국'이 됐다. 달러...",
          "pubDate": "Thu, 09 Jul 2026 07:00:00 +0900"
        },
        {
          "title": "\"SK하이닉스 40조 달러 유입 기대\"...환율 장중 1490원대로 '뚝'",
          "link": "https://www.ebn.co.kr/news/articleView.html?idxno=1715641",
          "description": "SK하이닉스의 미국 나스닥 미국주식예탁증서(ADR) 상장을 앞두고 대규모 달러 자금 유입 기대가 커진 데다 외국인 투자자가 국내 증시에서 순매수로 돌아서면서 환율 하락을 이끌었다. 8일 서울외환시장에서 원·달러...",
          "pubDate": "Thu, 09 Jul 2026 06:52:00 +0900"
        },
        {
          "title": "SK하이닉스, 10일 나스닥 상장…최태원 회장이 직접 챙긴다",
          "link": "https://n.news.naver.com/mnews/article/448/0000625363?sid=101",
          "description": "최태원 SK그룹 회장이 SK하이닉스의 미국주식예탁증서(ADR) 나스닥 상장을 계기로 미국을 찾는다. 나스닥 상장 기념식에 참석해 글로벌 투자자들과 소통하고, 주요 고객사들과 만나 인공지능(AI) 메모리 협력 확대...",
          "pubDate": "Thu, 09 Jul 2026 06:51:00 +0900"
        },
        {
          "title": "한시금지? 유한양행 덮친 공매도, 서정진도 불만 \"하락주범 vs 거품제거...",
          "link": "https://n.news.naver.com/mnews/article/417/0001150898?sid=101",
          "description": "미국과 유럽 등 주요 자본시장에서 공매도를 부정적으로 보기보단 시장 효율성을 높이는 제도로 평가하는 이유다. 강경훈 동국대학교 경영학과 교수는 \"공매도가 사라진다면 주식 시장이 과열됐을 때 억누를 수 있는...",
          "pubDate": "Thu, 09 Jul 2026 06:51:00 +0900"
        },
        {
          "title": "최태원 SK하이닉스 나스닥 상장에 미국행…주요 빅테크 기업들과 회동 ...",
          "link": "https://n.news.naver.com/mnews/article/021/0002803395?sid=101",
          "description": "연합뉴스 SK하이닉스의 미국주식예탁증서(ADR) 나스닥 상장을 계기로 최태원 SK그룹 회장이 방미길에 나선다. ADR 상장은 AI 인프라 확산의 핵심 기업으로 자리매김한 SK하이닉스의 기업가치를 글로벌 자본시장에서...",
          "pubDate": "Thu, 09 Jul 2026 06:50:00 +0900"
        },
        {
          "title": "SK하이닉스 나스닥 입성…최태원, AI 메모리 경쟁력 직접 세일즈",
          "link": "https://www.ebn.co.kr/news/articleView.html?idxno=1715640",
          "description": "최태원 SK그룹 회장이 SK하이닉스의 미국주식예탁증서(ADR) 나스닥 상장을 계기로 미국을 방문한다. 이번 방미는 글로벌 투자자들에게 SK하이닉스의 AI 메모리 경쟁력과 미래 성장성을 적극 알리는 동시에, 핵심...",
          "pubDate": "Thu, 09 Jul 2026 06:50:00 +0900"
        },
        {
          "title": "분석가 \"비트코인, 이란 사태 여파로 5만 6,550달러까지 하락 가능\"",
          "link": "http://coinreaders.com/246821",
          "description": "이어 도널드 트럼프 미국 대통령이 7월 8일 휴전이 종료됐다고 언급하면서 시장 불안이 확대됐다. 이 여파로 암호화폐뿐 아니라 주식시장도 약세를 보였고, 국제유가는 며칠간의 하락세를 끝내고 급등했다. 다만...",
          "pubDate": "Thu, 09 Jul 2026 06:48:00 +0900"
        },
        {
          "title": "스페이스X의 굴욕… 결국 상장가 밑으로 추락",
          "link": "https://n.news.naver.com/mnews/article/029/0003036106?sid=101",
          "description": "일론 머스크가 이끄는 미국 우주기업 스페이스X의 주가가 결국 상장가 아래로 떨어졌다. 이에 따라 상장... 스페이스 주식을 매입하고 있다. 하지난 편입 첫날에는 주가가 6.8% 폭락했다. 스페이스X는 우주와 AI...",
          "pubDate": "Thu, 09 Jul 2026 06:43:00 +0900"
        },
        {
          "title": "미국증시 유가·금리 압박에도 나스닥 반등…엔비디아·반도체주 선별 ...",
          "link": "https://www.topstarnews.net/news/articleView.html?idxno=16128404",
          "description": "다우와 S&P500은 하락했지만, 엔비디아와 반도체주가 반등하면서 나스닥은 장 막판 상승 전환했다.... ○ 미·이란 긴장에 다우 급락, 나스닥은 막판 반등 8일(미 동부시간) 뉴욕증권거래소에서 S&P500 지수는...",
          "pubDate": "Thu, 09 Jul 2026 06:56:00 +0900"
        },
        {
          "title": "[글로벌증시] 뉴욕증시, 중동 긴장·유가 급등에 혼조 마감",
          "link": "https://n.news.naver.com/mnews/article/422/0000883130?sid=101",
          "description": "기술주 중심의 나스닥을 제외하고는 모두 하락 마감했는데요. 어떻게 보셨습니까? 반도체주 반등이 나스닥을 방어한 것으로 보이는데요. 마이크론과 엔비디아 등이 모두 상승하면서 필라델피아 반도체 지수도 2...",
          "pubDate": "Thu, 09 Jul 2026 06:55:00 +0900"
        },
        {
          "title": "뉴욕증시, 미·이란 긴장 재고조에 혼조 마감…다우 1.1%↓",
          "link": "https://www.getnews.co.kr/news/articleView.html?idxno=874551",
          "description": "반면 인공지능(AI) 반도체 등 기술주 중심의 나스닥 종합지수는 전장보다 51.96포인트(0.20%) 오른 25,870.65에... 줄였고, 나스닥 지수는 장 막판 상승 전환했다. 대형 기술주들의 호재가 나스닥의 반등을 이끌었다....",
          "pubDate": "Thu, 09 Jul 2026 06:54:00 +0900"
        },
        {
          "title": "뉴욕증시, 미·이란 긴장 재고조 속 혼조...다우 1.09%↓",
          "link": "https://n.news.naver.com/mnews/article/629/0000514482?sid=101",
          "description": "스탠더드앤드푸어스(S&P)500지수는 0.28% 내린 7,482.71에, 기술주 중심의 나스닥 종합지수는 0.2% 오른 25,870.... 줄였고, 나스닥은 장 막판 상승 전환했다. 중국의 엔비디아 인공지능(AI) 칩 수요 회복 기대와 애플의 대규모...",
          "pubDate": "Thu, 09 Jul 2026 06:54:00 +0900"
        },
        {
          "title": "뉴욕증시, 반도체주 반등…엔비디아 3%대 급등 견인",
          "link": "https://www.bntnews.co.kr/article/view/bnt202607090007",
          "description": "나스닥 종합지수는 전장보다 51.96포인트(0.20%) 오른 25,870.65에 각각 장을 마감했다. S&P500 구성 종목 가운데 400개 종목이 하락하는 등 시장 전반에 매도세가 확산됐지만, 반도체주가 낙폭을 만회하면서 나스닥은...",
          "pubDate": "Thu, 09 Jul 2026 06:54:00 +0900"
        },
        {
          "title": "[오늘의 글로벌마켓] 뉴욕증시, 유가 급등에도 대형 반도체주 반등에 나...",
          "link": "http://www.opinionnews.co.kr/news/articleView.html?idxno=141253",
          "description": "다만 대형 기술주들의 개별 호재 소식이 전해지면서 상승하자, 나스닥 지수는 소폭 상승세로 거래를... 71로 거래를 마쳤고, 기술주 중심의 나스닥 지수는 전일대비 51.96포인트(0.20%) 오른 2만5870.65로 거래를...",
          "pubDate": "Thu, 09 Jul 2026 06:52:00 +0900"
        },
        {
          "title": "AI 기대 너무 커졌다…골드만 \"이번 어닝시즌은 가이던스가 좌우\"",
          "link": "https://www.pinpointnews.co.kr/news/articleView.html?idxno=466833",
          "description": "골드만삭스는 S&P500 상장기업들의 올해 2분기 순이익 증가율 컨센서스를 22% 수준으로 제시했다. 절대적인 실적은 견조하지만 이미 주가에 상당 부분 선반영된 만큼 투자자들의 눈높이를 다시 뛰어넘기는 쉽지 않을...",
          "pubDate": "Thu, 09 Jul 2026 06:58:00 +0900"
        }
      ]
    },
    "all": {
      "summary": "오늘 주요 뉴스를 불러오지 못했습니다.",
      "items": [
        {
          "title": "[7월8일] \"최고 모델이 공짜\"…오픈AI·앤트로픽이 무료 토큰 경쟁에 나...",
          "link": "https://www.aitimes.com/news/articleView.html?idxno=212534",
          "description": "이어 7일 주요 뉴스입니다. ■ 업스테이지 \"솔라 오픈 2로 3D 게임까지 빌드\"...자체 모델 성능 입증 김성훈 업스테이지 대표가 자체 모델로 3D 게임을 구현하는 데 성공했다고 밝혔습니다. 최근 AI 업계에서 유행하는...",
          "pubDate": "Thu, 09 Jul 2026 07:00:00 +0900"
        },
        {
          "title": "[모닝와이드] 오늘의 주요뉴스",
          "link": "https://n.news.naver.com/mnews/article/055/0001370932?sid=102",
          "description": "1. 시간당 70mm 장맛비…하천 범람, 농경지 침수 충남 계룡, 전남 담양과 전북 임실에 시간당 70mm의 폭우가 쏟아졌습니다. 충청과 호남에는 오늘(9일)까지 최대 200㎜, 중부 지방에도 최대 150mm의 폭우가 내릴 것으로...",
          "pubDate": "Thu, 09 Jul 2026 06:07:00 +0900"
        },
        {
          "title": "1부 오늘의 주요뉴스",
          "link": "https://n.news.naver.com/mnews/article/214/0001510486?sid=102",
          "description": "◀ 앵커 ▶ 미군이 이틀째 이란에 대한 추가 공습에 나섰습니다. 트럼프 대통령은 전면전 확대는 아니라고 선을 그었지만 전 최고지도자의 장례 기간 중인 이란이 내부 결속을 다지면서 다시 긴장감이 높아지고...",
          "pubDate": "Thu, 09 Jul 2026 06:01:00 +0900"
        },
        {
          "title": "[미리보는 이데일리 신문] 부모님 찬스 없으면 서울 전세도 못산다",
          "link": "https://n.news.naver.com/mnews/article/018/0006325644?sid=101",
          "description": "다음은 2026년 7월 9일자 이데일리 신문 주요 뉴스다. △1면 부모님 찬스 없으면 서울 전세도 못산다 AI 성장세지만 속도는 둔화… ‘메모리 정점’ 공포 확산 KB국민銀 주담대 한도 내일부터 6억→3억 트럼프 “이란과...",
          "pubDate": "Wed, 08 Jul 2026 22:47:00 +0900"
        },
        {
          "title": "[제주 주요뉴스] 압수수색 차일피일…하귀농협 수사 지지부진 외",
          "link": "https://n.news.naver.com/mnews/article/056/0012214306?sid=102",
          "description": "",
          "pubDate": "Wed, 08 Jul 2026 20:16:00 +0900"
        },
        {
          "title": "천둥·번개 동반 60mm 물폭탄…오늘 밤 고비",
          "link": "https://n.news.naver.com/mnews/article/449/0000352069?sid=102",
          "description": "오늘의 주요뉴스입니다. 장마가 커지면서 비 피해가 잇따르고 있습니다. 침수 피해 살펴봅니다. 여고생 살인범 장윤기, 수사팀이, 경찰 출신 장윤기 아버지에게 수사 힌트까지 알려 준 정황이 나왔습니다. 단독...",
          "pubDate": "Wed, 08 Jul 2026 19:08:00 +0900"
        },
        {
          "title": "비트코인, 중동 긴장 재점화에 6만2,000달러 하회",
          "link": "https://www.tokenpost.kr/news/cryptocurrency/375964",
          "description": "따라 방향이 자주 바뀌는 구간이기 때문에 무리한 단기 추격 매수는 위험할 수 있습니다. 분할 매수와 현금 비중 유지, 그리고 주요 뉴스 흐름을 확인하는 전략이 비교적 안정적인 대응으로 평가됩니다. TP AI 유의사항",
          "pubDate": "Wed, 08 Jul 2026 18:52:00 +0900"
        },
        {
          "title": "[데일리픽] 도지코인 40억개 입금 폭탄…AI 업계 '자체 칩' 개발 대세로",
          "link": "https://www.digitaltoday.co.kr/news/articleView.html?idxno=682434",
          "description": "디지털 경제 미디어 디지털투데이가 매일 아침, 주요 뉴스를 AI가 짚어주는 멀티미디어 뉴스 서비스를 제공합니다. 디지털투데이 텔레그램 채널에서 만나보세요. (매일 아침 06시 30분 업로드)",
          "pubDate": "Wed, 08 Jul 2026 17:06:00 +0900"
        },
        {
          "title": "민주당이 간과한 흥미로운 사실, 서울은 왜 '보수 우위 구도'가 됐나",
          "link": "https://n.news.naver.com/mnews/article/047/0002521958?sid=102",
          "description": "http://www.firenzedt.com/news/articleView.html?idxno=33061 필자 최병천은 현재 신성장경제연구소 소장이고, 명지대 교수이다. 민주연구원 부원장, 서울시 정책보좌관, 국회 보좌관 등을 역임했다. 저서로 ,",
          "pubDate": "Thu, 09 Jul 2026 07:01:00 +0900"
        },
        {
          "title": "'꼬마빌딩' 사후 감정평가액이 시가로 인정되려면? [린의 행정과 법률]",
          "link": "https://n.news.naver.com/mnews/article/015/0005307937?sid=102",
          "description": "이는 동일한 경제적 가치에 동일한 납세 부담을 부과하겠다는 '시가주의 선언'입니다. 그러나 비주거용 부동산은 거래가 부족해 신고 당시에는 시가를 확인하기 어려운 경우가 많습니다. 공시가액 현실화율이 낮아 시가가...",
          "pubDate": "Thu, 09 Jul 2026 07:01:00 +0900"
        },
        {
          "title": "'저가 경쟁 끝'…LCC, '다각화·통합·프리미엄화'로 전략 수정",
          "link": "https://n.news.naver.com/mnews/article/031/0001040823?sid=101",
          "description": "규모의 경제 확보 등으로 생존 전략의 무게중심을 옮기고 있다. 국내 LCC 1위인 제주항공은 단순한 항공운송... 또한 항공기 구매와 부품 조달에서도 규모의 경제를 확보할 수 있어 국내 최대 LCC가 탄생할 가능성이 높다....",
          "pubDate": "Thu, 09 Jul 2026 07:01:00 +0900"
        },
        {
          "title": "“공공 의료정보 플랫폼 구축...응급환자 ‘골든타임’ 확보 가능”",
          "link": "https://n.news.naver.com/mnews/article/011/0004639702?sid=103",
          "description": "서 원장은 8일 서울경제신문과의 인터뷰에서 공공의료 혁신의 핵심 과제로 인공지능(AI)·클라우드 기반 병원정보시스템(HIS) 구축을 꼽았다. 공공병원 간 의료데이터를 표준화해 진료 연속성을 높이고 불필요한 의료...",
          "pubDate": "Thu, 09 Jul 2026 07:01:00 +0900"
        },
        {
          "title": "JTBC 대표 예능 되겠네…이효리→서장훈, 청춘들 ‘찐 고민’ 담은 ‘연...",
          "link": "https://m.entertain.naver.com/article/241/0003519036",
          "description": "‘이숙캠’이 육아 고충, 경제적 어려움, 이혼 등 부부들의 갈등을 다룬다면 ‘연애전쟁’은 청춘들의 연애 고민을 깊게 들여다본다. 예를 들면 바쁜 직장 생활로 인해 서로 만날 시간이 없는 커플들의 갈등이나 워킹...",
          "pubDate": "Thu, 09 Jul 2026 07:00:00 +0900"
        },
        {
          "title": "나토서 K방산 띄운 李대통령…몽골로 출국",
          "link": "https://www.etoday.co.kr/news/view/2601798",
          "description": "정부는 핵심광물 개발과 자원 협력을 비롯해 에너지, 인프라, 물류 등 경제협력 확대 방안도 함께 논의할 계획이다. 나토 정상회의에서 방산과 원전 협력을 확대했다면, 몽골에서는 핵심광물과 공급망 협력을 더해...",
          "pubDate": "Thu, 09 Jul 2026 07:00:00 +0900"
        },
        {
          "title": "[기획] 스텔란티스코리아, 이익 깎는 최저가 승부수",
          "link": "https://www.startuptoday.co.kr/news/articleView.html?idxno=806047",
          "description": "방실 대표는 올 뉴 5008 출시 당시 \"한국 시장을 위해 경쟁력 있는 가격을 책정한 만큼 패밀리 SUV 선택에서 새로운 대안을 찾고 있는 고객들에게 매력적인 선택지가 될 것\"이라고 말했다. 오늘경제",
          "pubDate": "Thu, 09 Jul 2026 07:00:00 +0900"
        }
      ]
    }
  }
}
